[
    {
        "酒名":"羅亞爾河Asteria璀璨星夜氣泡酒",
        "簡介":"帶有老香檳味道的羅亞爾河氣泡酒",
        "參考價格":589,
        "產區":"Loire",
        "國家":"法國",
        "酒莊(廠)":"Cremant de loire Asteria",
        "葡萄品種":"Chenin Blanc(100%)",
        "購買通路":"大潤發",
        "年份":"無年",
        "酒精濃度":0.12,
        "甜度":1,
        "酸度":4,
        "飽滿度":5,
        "適合搭配食物":"沙拉",
        "品酒筆記":"帶有焦糖、不甜雪莉酒與烤麵包香氣，有老香檳的錯覺，氣泡細緻。3.5顆星",
        "URL":"https:\/\/littlewine.com.tw\/wine\/Detail.aspx?title=%e5%b8%b6%e6%9c%89%e8%80%81%e9%a6%99%e6%aa%b3%e5%91%b3%e9%81%93%e7%9a%84%e7%be%85%e4%ba%9e%e7%88%be%e6%b2%b3%e6%b0%a3%e6%b3%a1%e9%85%92&Wine=%e7%be%85%e4%ba%9e%e7%88%be%e6%b2%b3Asteria%e7%92%80%e7%92%a8%e6%98%9f%e5%a4%9c%e6%b0%a3%e6%b3%a1%e9%85%92"
    },
    {
        "酒名":"Granit Vieilles Vignes Coteaux Bourguignons Rouge",
        "簡介":"曼妙優雅的老藤勃根地",
        "參考價格":990,
        "產區":"Coteaux Bourguignons",
        "國家":"法國",
        "酒莊(廠)":"Domaine Masse",
        "葡萄品種":"Pinot Noir(100%)",
        "購買通路":"全聯S店",
        "年份":"2022年",
        "酒精濃度":0.13,
        "甜度":1,
        "酸度":4,
        "飽滿度":4,
        "適合搭配食物":"紅肉,伊比利火腿",
        "品酒筆記":"40年老藤黑皮諾，在十度的低溫下冷浸漬4天，並在控溫不鏽鋼與酒泥陳釀10個月，帶有飽滿新鮮的蔓越莓、紅醋栗等紅色果香，稍微醒開還有淡淡松露氣息，單寧柔滑，酸度宜人，是款口感優雅不失層次的老藤勃根地紅酒。 4顆星，這款只有全聯S店才有。",
        "URL":"https:\/\/littlewine.com.tw\/wine\/Detail.aspx?title=%e6%9b%bc%e5%a6%99%e5%84%aa%e9%9b%85%e7%9a%84%e8%80%81%e8%97%a4%e5%8b%83%e6%a0%b9%e5%9c%b0&Wine=Granit+Vieilles+Vignes+Coteaux+Bourguignons+Rouge"
    },
    {
        "酒名":"Vieilles Vignes Bourgogne Chardonnay",
        "簡介":"適合搭配白醬義大利麵的勃根地白酒",
        "參考價格":990,
        "產區":"Bourgogne",
        "國家":"法國",
        "酒莊(廠)":"Domaine Masse",
        "葡萄品種":"Chardonnay(100%)",
        "購買通路":"全聯S店",
        "年份":"2023年",
        "酒精濃度":0.13,
        "甜度":1,
        "酸度":4,
        "飽滿度":5,
        "適合搭配食物":"白醬義大利麵",
        "品酒筆記":"香草、堅果與熱帶水果氣息，口感飽滿圓潤，酸度不特別高，適合奶油鮭魚或是白醬義大利麵。",
        "URL":"https:\/\/littlewine.com.tw\/wine\/Detail.aspx?title=%e9%81%a9%e5%90%88%e6%90%ad%e9%85%8d%e7%99%bd%e9%86%ac%e7%be%a9%e5%a4%a7%e5%88%a9%e9%ba%b5%e7%9a%84%e5%8b%83%e6%a0%b9%e5%9c%b0%e7%99%bd%e9%85%92&Wine=Vieilles+Vignes+Bourgogne+Chardonnay"
    },
    {
        "酒名":"Faustino Rivero Ulecia Rioja Reserva",
        "簡介":"酒體偏淡的Rioja",
        "參考價格":279,
        "產區":"Rioja Reserva",
        "國家":"西班牙",
        "酒莊(廠)":"Faustino Rivero Ulecia",
        "葡萄品種":"Tempranillo and Garnacha(100%)",
        "購買通路":"好市多",
        "年份":"2018年",
        "酒精濃度":0.135,
        "甜度":1,
        "酸度":4,
        "飽滿度":4,
        "適合搭配食物":"牛肉",
        "品酒筆記":"經過12個月橡木桶熟成，帶有櫻桃、梅子與木桶香氣，酸度不錯，單寧適中，可惜酒體偏淡，適合搭餐。3.5顆星。",
        "URL":"https:\/\/littlewine.com.tw\/wine\/Detail.aspx?title=%e9%85%92%e9%ab%94%e5%81%8f%e6%b7%a1%e7%9a%84Rioja&Wine=Faustino+Rivero+Ulecia+Rioja+Reserva"
    },
    {
        "酒名":"Baron Maxime brut Gold Reserve blanc de Blancs",
        "簡介":"輕鬆淡雅的白中白氣泡酒",
        "參考價格":359,
        "產區":"Limoux",
        "國家":"法國",
        "酒莊(廠)":"Baron Maxime",
        "葡萄品種":"Ugni Blanc, Colombard, Chenin blanc and Chardonnay 混合(100%)",
        "購買通路":"好市多",
        "年份":"無年",
        "酒精濃度":0.12,
        "甜度":1,
        "酸度":4,
        "飽滿度":4,
        "適合搭配食物":"海鮮",
        "品酒筆記":"好市多新品，來自於Limux 產區，以Ugni Blanc, Colombard, Chenin blanc and Chardonnay 混合而成，帶有青蘋果、柑橘香氣，氣泡柔和，口感淡雅，是款輕鬆的氣泡酒。3.5顆星推薦\n\n背膠上有個神奇的標籤，當溫度對的時候（7-9度），會出現綠色的皇冠。",
        "URL":"https:\/\/littlewine.com.tw\/wine\/Detail.aspx?title=%e8%bc%95%e9%ac%86%e6%b7%a1%e9%9b%85%e7%9a%84%e7%99%bd%e4%b8%ad%e7%99%bd%e6%b0%a3%e6%b3%a1%e9%85%92&Wine=Baron+Maxime+brut+Gold+Reserve+blanc+de+Blancs"
    },
    {
        "酒名":"Pastourelle de Clerc Milon",
        "簡介":"還需要多放幾年的雙人跳二軍",
        "參考價格":1188,
        "產區":"Pauillac",
        "國家":"法國",
        "酒莊(廠)":"Chateau Clerc Milon",
        "葡萄品種":"Merlot(51%) ,Cabernet Sauvignon (40%) ,Cabernet Franc (8%) ,Carmenere (1%)",
        "購買通路":"創潮酒坊",
        "年份":"2020年",
        "酒精濃度":0.135,
        "甜度":1,
        "酸度":4,
        "飽滿度":5,
        "適合搭配食物":"羊排",
        "品酒筆記":"一開始表現普普，瓶醒兩小時後開始出現濃郁的黑色水果香氣，適度的木質調性，單寧依舊明顯，醒4小時後，尾韻帶些咖啡香氣。建議可以再放個3年，或是要拉長醒酒時間兩個小時以上。4顆星推薦。",
        "URL":"https:\/\/littlewine.com.tw\/wine\/Detail.aspx?title=%e9%82%84%e9%9c%80%e8%a6%81%e5%a4%9a%e6%94%be%e5%b9%be%e5%b9%b4%e7%9a%84%e9%9b%99%e4%ba%ba%e8%b7%b3%e4%ba%8c%e8%bb%8d&Wine=Pastourelle+de+Clerc+Milon"
    },
    {
        "酒名":"Mapu Merlot",
        "簡介":"適合新手入門的智利 Merlot 紅酒",
        "參考價格":350,
        "產區":"Maipo Valley",
        "國家":"智利",
        "酒莊(廠)":"Baron Philippe de Rothschild",
        "葡萄品種":"Merlot(100%)",
        "購買通路":"橡木桶洋酒",
        "年份":"2022年",
        "酒精濃度":0.14,
        "甜度":1,
        "酸度":1,
        "飽滿度":4,
        "適合搭配食物":"牛排",
        "品酒筆記":"MAPU 是連鎖葡萄酒專賣店橡木桶的長年品相，也是 Baron Philippe de Rothschild 旗下的一個系列，這款是他們酒莊最初階款，酒標已經換了好幾輪，剛開始學喝葡萄酒時，很常喝，最近看到特價，又想買來試試。\n\nMAPU這款有兩種品種，一種是Cabernet sauvignon，這款是 Merlot，會選 Merlot 主要是，便宜的智利Cabernet sauvignon 常常帶有青椒味，小資個人不喜歡，所以為了保險起見，所以選擇 Merlot。\n\n散發櫻桃、菸草風味，單寧稍稍明顯，酸度不錯，喝起來還是有一點架構在，不會太平，是款日常普飲的智利紅酒，也很適合入門新手。\n\n最近特價4瓶只要一張小朋友多一點點，當作日常餐酒還是很可以的。4顆星推薦。\n",
        "URL":"https:\/\/littlewine.com.tw\/wine\/Detail.aspx?title=%e9%81%a9%e5%90%88%e6%96%b0%e6%89%8b%e5%85%a5%e9%96%80%e7%9a%84%e6%99%ba%e5%88%a9+Merlot+%e7%b4%85%e9%85%92&Wine=Mapu+Merlot"
    },
    {
        "酒名":"Beringer Founders' Estate Cabernet Sauvignon",
        "簡介":"甜美的美國入門搭餐酒",
        "參考價格":549,
        "產區":"California",
        "國家":"美國",
        "酒莊(廠)":"Beringer",
        "葡萄品種":"Cabernet Sauvignon(100%)",
        "購買通路":"好市多",
        "年份":"2021年",
        "酒精濃度":0.138,
        "甜度":2,
        "酸度":3,
        "飽滿度":5,
        "適合搭配食物":"牛排",
        "品酒筆記":"帶有黑棗、黑李與蜜餞風味，口感甜美，單寧柔順的酒款。適合搭配牛排，也很適合很討厭酸澀葡萄酒的初學者。3.5顆星。",
        "URL":"https:\/\/littlewine.com.tw\/wine\/Detail.aspx?title=%e7%94%9c%e7%be%8e%e7%9a%84%e7%be%8e%e5%9c%8b%e5%85%a5%e9%96%80%e6%90%ad%e9%a4%90%e9%85%92&Wine=Beringer+Founders%27+Estate+Cabernet+Sauvignon"
    },
    {
        "酒名":"Wente Merlot",
        "簡介":"適合牛排或聚餐的美國Wente Merlot 紅酒",
        "參考價格":619,
        "產區":"Central coast",
        "國家":"美國",
        "酒莊(廠)":"Wente",
        "葡萄品種":"\nＭerlot(100%)",
        "購買通路":"橡木桶洋酒",
        "年份":"2021年",
        "酒精濃度":0.135,
        "甜度":1,
        "酸度":4,
        "飽滿度":5,
        "適合搭配食物":"牛排",
        "品酒筆記":"Wente 也是橡木桶架上的長年品項，自己也是喝很多次。\n\n小資對於加州 Merlot的印象很好，不會太柔軟，很有自己的風格。 這款來自於 加州 Central coast 的 Merlot，帶有黑莓、可可以及適切的桶位，剛剛好的單寧，有架構不會過澀， 這種算是中價位，適合帶去聚餐、吃牛排，也是我去橡木桶看到價錢優惠，就會毫不思索結帳的酒款，建議醒酒30分鐘。4顆星推薦。",
        "URL":"https:\/\/littlewine.com.tw\/wine\/Detail.aspx?title=%e9%81%a9%e5%90%88%e7%89%9b%e6%8e%92%e6%88%96%e8%81%9a%e9%a4%90%e7%9a%84%e7%be%8e%e5%9c%8bWente+Merlot+%e7%b4%85%e9%85%92&Wine=Wente+Merlot+"
    },
    {
        "酒名":"Gulfi Sanlorenzo Sicilia",
        "簡介":"花香、酸度皆迷人的西西里島單一園Nero d'Avola",
        "參考價格":3380,
        "產區":"Sicilia",
        "國家":"義大利",
        "酒莊(廠)":"Gulfi",
        "葡萄品種":"Nero d'Avola(100%)",
        "購買通路":"Frenchie-Frenchie",
        "年份":"2015年",
        "酒精濃度":0.14,
        "甜度":1,
        "酸度":5,
        "飽滿度":5,
        "適合搭配食物":"紅肉",
        "品酒筆記":"這應該是小資喝到印象最深的Nero d'Avola，雖然是2015年的酒，但是絲毫沒有老態，帶有迷人的紅色梅子、草本與花香，酸度明亮，口感均衡，尾韻綿長，小小一杯，就可以喝很久。4顆星推薦\n",
        "URL":"https:\/\/littlewine.com.tw\/wine\/Detail.aspx?title=%e8%8a%b1%e9%a6%99%e3%80%81%e9%85%b8%e5%ba%a6%e7%9a%86%e8%bf%b7%e4%ba%ba%e7%9a%84%e8%a5%bf%e8%a5%bf%e9%87%8c%e5%b3%b6%e5%96%ae%e4%b8%80%e5%9c%92Nero+d%27Avola&Wine=Gulfi+Sanlorenzo+Sicilia"
    },
    {
        "酒名":"Chateau La Lagune 2015",
        "簡介":"香氣幽韻高雅的 Chateau La Lagune 2015",
        "參考價格":2500,
        "產區":"Haut Medoc",
        "國家":"法國",
        "酒莊(廠)":"Chateau La Lagune",
        "葡萄品種":"Cabernet Sauvignon (60%) ,Merlot (30%) ,Petit Verdot (5%)",
        "購買通路":"網路",
        "年份":"2015年",
        "酒精濃度":0.14,
        "甜度":1,
        "酸度":4,
        "飽滿度":5,
        "適合搭配食物":"羊排",
        "品酒筆記":"波爾多三級酒莊，2004 年Caroline Frey 接手後，開始使用自然動力法，以65% Cabernet Sauvignon 、30% Merlot 與 5% Petit Verdot 混合而成，以50%酒液在新橡木桶陳年，雖然已經是9年前的酒，但是現在喝起來依舊很有活力，香氣幽雅高雅，帶著迷人的酸度，單寧依舊緊致，還有繼續的成年空間。。4.5顆星",
        "URL":"https:\/\/littlewine.com.tw\/wine\/Detail.aspx?title=%e9%a6%99%e6%b0%a3%e5%b9%bd%e9%9f%bb%e9%ab%98%e9%9b%85%e7%9a%84+Chateau+La+Lagune+2015&Wine=Chateau+La+Lagune+2015"
    },
    {
        "酒名":"Moulin du Château La Lagune",
        "簡介":"果味濃郁的Chateau La Lagune二軍",
        "參考價格":720,
        "產區":"Haut Medoc\n\n",
        "國家":"法國",
        "酒莊(廠)":"Château La Lagune",
        "葡萄品種":"Merlot(60%) ,Cabernet Sauvignon (33%) ,Petit Verdot (7%)",
        "購買通路":"網路",
        "年份":"2019年",
        "酒精濃度":0.145,
        "甜度":1,
        "酸度":4,
        "飽滿度":5,
        "適合搭配食物":"牛排",
        "品酒筆記":"Chateau La Lagune的二軍酒Moulin du Château La Lagune，但以30% Cabernet Sauvignon 60% Merlot 以及7 % Petit Verdot 混合而成，12 個月法國橡木桶陳年，其中40% 是新桶，帶有濃郁的紫羅蘭與黑醋栗，入口帶些煙燻與肉乾，架構清楚，單寧緊實。4顆星",
        "URL":"https:\/\/littlewine.com.tw\/wine\/Detail.aspx?title=%e6%9e%9c%e5%91%b3%e6%bf%83%e9%83%81%e7%9a%84Chateau+La+Lagune%e4%ba%8c%e8%bb%8d&Wine=Moulin+du+Ch%c3%a2teau+La+Lagune"
    },
    {
        "酒名":"南法小豬-Merlot",
        "簡介":"簡單的日常餐酒藍色南法小豬-Merlot",
        "參考價格":379,
        "產區":"Pays D'OC",
        "國家":"法國",
        "酒莊(廠)":"Le Petit Cochonnet",
        "葡萄品種":"Merlot(100%)",
        "購買通路":"家樂福超市",
        "年份":"2022年",
        "酒精濃度":0.135,
        "甜度":1,
        "酸度":3,
        "飽滿度":4,
        "適合搭配食物":"漢堡",
        "品酒筆記":"南法小豬全新品相-Merlot，今年四月去南法小豬原廠時有喝過。紅色水果風味，酒體中等，口感圓潤，單寧不強，尾韻帶些黑苦巧克力風味。不是什麼多厲害的酒款，不用期待太高，就是南法人的日常餐酒，可以搭牛排或是漢堡。3.5顆星。",
        "URL":"https:\/\/littlewine.com.tw\/wine\/Detail.aspx?title=%e7%b0%a1%e5%96%ae%e7%9a%84%e6%97%a5%e5%b8%b8%e9%a4%90%e9%85%92%e8%97%8d%e8%89%b2%e5%8d%97%e6%b3%95%e5%b0%8f%e8%b1%ac-Merlot&Wine=%e5%8d%97%e6%b3%95%e5%b0%8f%e8%b1%ac-Merlot"
    },
    {
        "酒名":"Georges Duboeuf Orange Nouveau",
        "簡介":"青春成熟兼具的新橘酒",
        "參考價格":1064,
        "產區":"南法",
        "國家":"法國",
        "酒莊(廠)":"Georges Duboeuf",
        "葡萄品種":"Grenache Blanc(50%) ,Viognier (20%) ,Muscat (10%)",
        "購買通路":"橡木桶",
        "年份":"2024年",
        "酒精濃度":0.13,
        "甜度":1,
        "酸度":4,
        "飽滿度":5,
        "適合搭配食物":"沙拉或輕食",
        "品酒筆記":"這是由大酒廠 Georges Duboeuf 以50%Grenache Blanc、20 % Viognier 以及 10% Muscat 所釀造的新橘酒，散發飄逸的柑橘果香，給人一種自然酒的純粹；13%酒精濃度加上微微的單寧收斂感，尾韻帶些葡萄柚尾韻，讓這款新橘酒有著青春的活潑，也夾帶些許成熟的大人味。\n\n是近年最印象深刻的新酒，建議用勃根地酒杯喝。4顆星。",
        "URL":"https:\/\/littlewine.com.tw\/wine\/Detail.aspx?title=%e9%9d%92%e6%98%a5%e6%88%90%e7%86%9f%e5%85%bc%e5%85%b7%e7%9a%84%e6%96%b0%e6%a9%98%e9%85%92&Wine=Georges+Duboeuf+Orange+Nouveau"
    },
    {
        "酒名":"Torres Coronas Tempranillo",
        "簡介":"酸度迷人的西班牙 Tempranillo 混釀",
        "參考價格":690,
        "產區":"Catalunya",
        "國家":"西班牙",
        "酒莊(廠)":"Torres",
        "葡萄品種":"empranillo &Cabernet Sauvignon(100%)",
        "購買通路":"法蘭絲",
        "年份":"2020年",
        "酒精濃度":0.135,
        "甜度":1,
        "酸度":4,
        "飽滿度":4,
        "適合搭配食物":"紅肉",
        "品酒筆記":"西班牙知名大廠，櫻桃、李子等紅色水果，單寧適中帶韌，輕柔易喝不失架構。",
        "URL":"https:\/\/littlewine.com.tw\/wine\/Detail.aspx?title=%e9%85%b8%e5%ba%a6%e8%bf%b7%e4%ba%ba%e7%9a%84%e8%a5%bf%e7%8f%ad%e7%89%99+Tempranillo+%e6%b7%b7%e9%87%80&Wine=Torres+Coronas+Tempranillo"
    },
    {
        "酒名":"DOURTHE N°1 ROUGE",
        "簡介":"法國大廠的經典波爾多紅酒",
        "參考價格":860,
        "產區":"Bordeaux",
        "國家":"法國",
        "酒莊(廠)":"Dourthe",
        "葡萄品種":"Merlot, Cabernet Sauvignon and Petit Verdot(100%)",
        "購買通路":"法蘭絲,全聯",
        "年份":"2020年",
        "酒精濃度":0.145,
        "甜度":1,
        "酸度":4,
        "飽滿度":5,
        "適合搭配食物":"牛排,羊排",
        "品酒筆記":"來自於法國大廠杜道酒廠 Dourthe 1號紅酒。經典的波爾多紅酒，明顯的木桶香氣，紅黑色水果中夾帶些可可、胡椒氣味，單寧中上，建議醒酒30分鐘，口感會更甜美，搭配帶有油脂的牛排或是羊排。",
        "URL":"https:\/\/littlewine.com.tw\/wine\/Detail.aspx?title=%e6%b3%95%e5%9c%8b%e5%a4%a7%e5%bb%a0%e7%9a%84%e7%b6%93%e5%85%b8%e6%b3%a2%e7%88%be%e5%a4%9a%e7%b4%85%e9%85%92&Wine=DOURTHE+N%c2%b01+ROUGE"
    },
    {
        "酒名":"Champagne Louis Dumont Rose",
        "簡介":"均衡優雅的粉紅香檳",
        "參考價格":1099,
        "產區":"Champagne",
        "國家":"法國",
        "酒莊(廠)":"Louis Dumont",
        "葡萄品種":"Pinot Noir(50%) ,Pinot Meunier (20%) ,Chardonnay (30%)",
        "購買通路":"大潤發",
        "年份":"無年",
        "酒精濃度":0.12,
        "甜度":1,
        "酸度":4,
        "飽滿度":5,
        "適合搭配食物":"百搭",
        "品酒筆記":"喝了他們家三款香檳，這款最好喝。帶有淡雅的草莓與櫻桃香氣，迷人的酸度，口感均衡。",
        "URL":"https:\/\/littlewine.com.tw\/wine\/Detail.aspx?title=%e5%9d%87%e8%a1%a1%e5%84%aa%e9%9b%85%e7%9a%84%e7%b2%89%e7%b4%85%e9%a6%99%e6%aa%b3&Wine=Champagne+Louis+Dumont+Rose"
    },
    {
        "酒名":"Louis Dumont Premier Cru",
        "簡介":"青蘋果箱滿滿的香檳",
        "參考價格":1299,
        "產區":"Champagne",
        "國家":"法國",
        "酒莊(廠)":"Louis Dumont",
        "葡萄品種":"Pinot Noir(45%) ,Chardonnay (30%) ,Pinot Meunier (25%)",
        "購買通路":"大潤發",
        "年份":"無年",
        "酒精濃度":0.12,
        "甜度":1,
        "酸度":4,
        "飽滿度":5,
        "適合搭配食物":"百搭",
        "品酒筆記":"青蘋果香滿溢，口感飽滿，氣泡優雅，尾韻帶些葡萄柚尾韻。",
        "URL":"https:\/\/littlewine.com.tw\/wine\/Detail.aspx?title=%e9%9d%92%e8%98%8b%e6%9e%9c%e7%ae%b1%e6%bb%bf%e6%bb%bf%e7%9a%84%e9%a6%99%e6%aa%b3&Wine=Louis+Dumont+Premier+Cru"
    },
    {
        "酒名":"Chateau de Corcelles vieilles Vignes Beaujolais Villages Nouveau",
        "簡介":"跟草莓牛奶爆米花超搭的薄酒萊老藤新酒",
        "參考價格":1080,
        "產區":"Beaujolais Villages Nouveau",
        "國家":"法國",
        "酒莊(廠)":"Chateau de Corcelles",
        "葡萄品種":"Gamay(100%)",
        "購買通路":"法蘭絲",
        "年份":"\n2024年",
        "酒精濃度":0.125,
        "甜度":1,
        "酸度":4,
        "飽滿度":4,
        "適合搭配食物":"草莓牛奶爆米花",
        "品酒筆記":"帶有草莓、櫻桃香氣，口感輕盈柔順，由於是老藤葡萄，帶有更多複雜的口感，單寧絲滑，開瓶就好喝，是款不需等待，盡快開瓶享受的薄酒萊新酒，而且跟草莓牛奶爆米花絕搭。",
        "URL":"https:\/\/littlewine.com.tw\/wine\/Detail.aspx?title=%e8%b7%9f%e8%8d%89%e8%8e%93%e7%89%9b%e5%a5%b6%e7%88%86%e7%b1%b3%e8%8a%b1%e8%b6%85%e6%90%ad%e7%9a%84%e8%96%84%e9%85%92%e8%90%8a%e8%80%81%e8%97%a4%e6%96%b0%e9%85%92&Wine=Chateau+de+Corcelles+vieilles+Vignes+Beaujolais+Villages+Nouveau"
    },
    {
        "酒名":"Albert Bichot Beaujolais-Villages Nouveau",
        "簡介":"青春的滋味＿Albert Bichot 薄酒萊村莊級新酒",
        "參考價格":850,
        "產區":"Beaujolais-Villages",
        "國家":"法國",
        "酒莊(廠)":"Albert Bichot",
        "葡萄品種":"Gamay(100%)",
        "購買通路":"酩洋",
        "年份":"2024年",
        "酒精濃度":0.125,
        "甜度":1,
        "酸度":4,
        "飽滿度":4,
        "適合搭配食物":"各式中菜",
        "品酒筆記":"帶有迷人的草莓香氣，口感輕巧，酸度適中，像是一個剛結束畢業典禮的高中女生，以正面的態度迎向全新的大學生活。",
        "URL":"https:\/\/littlewine.com.tw\/wine\/Detail.aspx?title=%e9%9d%92%e6%98%a5%e7%9a%84%e6%bb%8b%e5%91%b3%ef%bc%bfAlbert+Bichot+%e8%96%84%e9%85%92%e8%90%8a%e6%9d%91%e8%8e%8a%e7%b4%9a%e6%96%b0%e9%85%92&Wine=Albert+Bichot+Beaujolais-Villages+Nouveau"
    },
    {
        "酒名":"GIANNI GAGLIARDO Villa M Bianco",
        "簡介":"與麻婆豆腐超搭的義大利微氣泡甜白酒",
        "參考價格":660,
        "產區":"Monferrato",
        "國家":"義大利",
        "酒莊(廠)":"GIANNI GAGLIARDO",
        "葡萄品種":"Moscato(100%)",
        "購買通路":"法蘭絲",
        "年份":"無年",
        "酒精濃度":0.05,
        "甜度":4,
        "酸度":3,
        "飽滿度":4,
        "適合搭配食物":"麻婆豆腐,甜點",
        "品酒筆記":"義大利的 Moscato 氣泡酒，微甜、帶有愉悅的氣泡感，冰涼飲用，口感非常討喜，適合搭配麻婆豆腐或是甜點。",
        "URL":"https:\/\/littlewine.com.tw\/wine\/Detail.aspx?title=%e8%88%87%e9%ba%bb%e5%a9%86%e8%b1%86%e8%85%90%e8%b6%85%e6%90%ad%e7%9a%84%e7%be%a9%e5%a4%a7%e5%88%a9%e5%be%ae%e6%b0%a3%e6%b3%a1%e7%94%9c%e7%99%bd%e9%85%92&Wine=GIANNI+GAGLIARDO+Villa+M+Bianco"
    },
    {
        "酒名":"Chateau des Jacques",
        "簡介":"適合搭配中式菜餚的薄酒萊村莊級產區紅酒",
        "參考價格":1300,
        "產區":"Moulin-A-Vent",
        "國家":"法國",
        "酒莊(廠)":"Maison Louis Jadot",
        "葡萄品種":"Gamay(100%)",
        "購買通路":"法蘭絲",
        "年份":"2021年",
        "酒精濃度":0.125,
        "甜度":1,
        "酸度":4,
        "飽滿度":4,
        "適合搭配食物":"中式菜餚",
        "品酒筆記":"來自於薄酒萊村莊級風車磨Moulin-A-Vent產區，帶有草莓、櫻桃、洛神花以及微微木桶風味，醒開後會帶點肉乾的味道；酸度曼妙，口感柔中帶勁，單寧細緻如織，易喝又不失架構的村莊級薄酒萊。村莊級薄酒萊是小資心目中最適合搭配中式菜餚的紅酒。",
        "URL":"https:\/\/littlewine.com.tw\/wine\/Detail.aspx?title=%e9%81%a9%e5%90%88%e6%90%ad%e9%85%8d%e4%b8%ad%e5%bc%8f%e8%8f%9c%e9%a4%9a%e7%9a%84%e8%96%84%e9%85%92%e8%90%8a%e6%9d%91%e8%8e%8a%e7%b4%9a%e7%94%a2%e5%8d%80%e7%b4%85%e9%85%92&Wine=Chateau+des+Jacques"
    },
    {
        "酒名":"Paul Jaboulet Aine La Chapelle",
        "簡介":"Hermitage La Chapelle小教堂 2006",
        "參考價格":8000,
        "產區":"Hermitage",
        "國家":"法國",
        "酒莊(廠)":"Paul Jaboulet Aine",
        "葡萄品種":"Syrah(100%)",
        "購買通路":"葡萄酒專賣店",
        "年份":"2006年",
        "酒精濃度":0.13,
        "甜度":1,
        "酸度":5,
        "飽滿度":5,
        "適合搭配食物":"燒烤",
        "品酒筆記":"Hermitage La Chapelle小教堂 2006，雖然距今已經18個年頭，依舊帶有迷人的酸度，內斂的大地、八仙果與陳皮香氣，單寧已經完全柔化，尾韻非常綿長。",
        "URL":"https:\/\/littlewine.com.tw\/wine\/Detail.aspx?title=Hermitage+La+Chapelle%e5%b0%8f%e6%95%99%e5%a0%82+2006&Wine=Paul+Jaboulet+Aine+La+Chapelle"
    },
    {
        "酒名":"L'Atelier Carmenere",
        "簡介":"單寧柔滑的智利Carmenere",
        "參考價格":579,
        "產區":"Colchagua Valley",
        "國家":"智利",
        "酒莊(廠)":"Humo Blanco",
        "葡萄品種":"Carmenere(100%)",
        "購買通路":"大潤發",
        "年份":"2022年",
        "酒精濃度":0.135,
        "甜度":1,
        "酸度":4,
        "飽滿度":5,
        "適合搭配食物":"燒烤",
        "品酒筆記":"來至於智利最知名的品種Carmenere，紅色水果帶些胡椒、辛香料以及淡淡的青椒味，口感柔滑，單寧如天鵝絨般柔順。採用蠟封，感覺質感很好。",
        "URL":"https:\/\/littlewine.com.tw\/wine\/Detail.aspx?title=%e5%96%ae%e5%af%a7%e6%9f%94%e6%bb%91%e7%9a%84%e6%99%ba%e5%88%a9Carmenere&Wine=L%27Atelier+Carmenere"
    },
    {
        "酒名":"Champagne Louis Dumont Brut",
        "簡介":"輕鬆易喝的入門香檳",
        "參考價格":1089,
        "產區":"Champagne",
        "國家":"法國",
        "酒莊(廠)":"Louis Dumont",
        "葡萄品種":"Pinot Noir(51%) ,Pinot Meunier (30%) ,Chardonnay (19%)",
        "購買通路":"大潤發",
        "年份":"無年",
        "酒精濃度":0.12,
        "甜度":1,
        "酸度":5,
        "飽滿度":5,
        "適合搭配食物":"生蠔",
        "品酒筆記":"帶淡淡的酵母、些微礦物感，夾雜一些青蘋果、柑橘風味，氣泡細緻，口感飽滿。",
        "URL":"https:\/\/littlewine.com.tw\/wine\/Detail.aspx?title=%e8%bc%95%e9%ac%86%e6%98%93%e5%96%9d%e7%9a%84%e5%85%a5%e9%96%80%e9%a6%99%e6%aa%b3&Wine=Champagne+Louis+Dumont+Brut"
    },
    {
        "酒名":"Valatiere Grande Reserve Carignan Vieilles Vignes",
        "簡介":"易喝不單調的老藤南法餐酒",
        "參考價格":369,
        "產區":"Languedoc-Roussillon",
        "國家":"法國",
        "酒莊(廠)":"Reunis de Cebazan",
        "葡萄品種":"Carignan(100%)",
        "購買通路":"大潤發",
        "年份":"2023年",
        "酒精濃度":0.125,
        "甜度":1,
        "酸度":4,
        "飽滿度":4,
        "適合搭配食物":"紅肉",
        "品酒筆記":"老藤 Carignan 來自於Languedoc-Roussillon 產區的餐酒。\n\n走的是紅色水果風味，酸度不錯，由於是老藤葡萄，讓酒體帶些多些複雜度，口感不會過於單一， 單寧柔順，是款易喝不會過於單調的餐酒，3.5顆星",
        "URL":"https:\/\/littlewine.com.tw\/wine\/Detail.aspx?title=%e6%98%93%e5%96%9d%e4%b8%8d%e5%96%ae%e8%aa%bf%e7%9a%84%e8%80%81%e8%97%a4%e5%8d%97%e6%b3%95%e9%a4%90%e9%85%92&Wine=Valatiere+Grande+Reserve+Carignan+Vieilles+Vignes"
    },
    {
        "酒名":"Wynns Black Label Cabernet Sauvignon",
        "簡介":"飽滿圓滑有層次的澳洲卡本內蘇維翁",
        "參考價格":1800,
        "產區":"Coonawarra",
        "國家":"澳洲",
        "酒莊(廠)":"Wynn",
        "葡萄品種":"Cabernet Sauvignon(100%)",
        "購買通路":"Wine O'Clock,LOCA Co",
        "年份":"2019年",
        "酒精濃度":0.138,
        "甜度":1,
        "酸度":4,
        "飽滿度":5,
        "適合搭配食物":"牛排",
        "品酒筆記":"嚴選酒莊位於庫納瓦拉產區terra rossa紅土葡萄園中，20%-25%最頂級的卡本內蘇維濃 (Cabernet Sauvignon)葡萄釀造。在法國新(30%)及舊橡木桶中陳放16個月。帶有黑色水果與木桶風味，口感飽滿圓滑，單寧適中，適合搭配牛排。",
        "URL":"https:\/\/littlewine.com.tw\/wine\/Detail.aspx?title=%e9%a3%bd%e6%bb%bf%e5%9c%93%e6%bb%91%e6%9c%89%e5%b1%a4%e6%ac%a1%e7%9a%84%e6%be%b3%e6%b4%b2%e5%8d%a1%e6%9c%ac%e5%85%a7%e8%98%87%e7%b6%ad%e7%bf%81&Wine=Wynns+Black+Label+Cabernet+Sauvignon"
    },
    {
        "酒名":"Georg Jensen Hallmark Cuvée",
        "簡介":"酒塞超美的喬治傑生旗艦銀氣泡酒",
        "參考價格":1680,
        "產區":"Tasmania",
        "國家":"澳洲",
        "酒莊(廠)":"Heemskerk",
        "葡萄品種":"Chardonnay(60%) ,Pinot Noir (40%)",
        "購買通路":"家樂福",
        "年份":"無年",
        "酒精濃度":0.12,
        "甜度":1,
        "酸度":4,
        "飽滿度":5,
        "適合搭配食物":"前菜",
        "品酒筆記":"不知道是不是改了配方？ 還是當初運送有問題？\n\n這款氣泡酒大家應該都喝過，喝過的人通常都保持非常保守的評價，甚至是偏負面的評價，認為就只有酒塞好看。\n\n老實說，小資幾年前喝過一次，真的不怎麼樣。\n\n喝起來很水，幾乎沒有味道。\n\n但是這次再喝，沒有印象中那麼糟，帶有柑橘果香，適中的氣泡，是款中規中矩不難喝的氣泡酒。\n\n但為什麼跟之前喝起來印象中差這麼多呢？\n\n不確定是不是改了配方？ (後來問過代理商沒有）\n\n所以我思考到的是保存問題。\n\n之前這款酒，台灣沒有代理商，我喝到的是澳洲代購進來的，是否有用低溫保存就不知道了。\n\n但是我確定，這款酒今天喝起來跟之前喝起來差很多，而且好很多，有改變我對這款酒的印象。\n\n之前被人覺得很廉價的酒瓶蓋設計，其實Pét-nat 的氣泡酒，也很多是用這種像是啤酒蓋的設計，打開後喝不完，直接用美的要命的氣泡酒塞保存就可以了，軟木塞反而不適合這樣的設計，\n\n而且有個高質感黑色立體紙袋，過年用來送禮是很可以的東西，家樂福、Mia C’bon可以買到，全聯也可以預購。",
        "URL":"https:\/\/littlewine.com.tw\/wine\/Detail.aspx?title=%e9%85%92%e5%a1%9e%e8%b6%85%e7%be%8e%e7%9a%84%e5%96%ac%e6%b2%bb%e5%82%91%e7%94%9f%e6%97%97%e8%89%a6%e9%8a%80%e6%b0%a3%e6%b3%a1%e9%85%92&Wine=Georg+Jensen+Hallmark+Cuv%c3%a9e"
    },
    {
        "酒名":"法國南法穆雷蒂GSM混釀紅酒",
        "簡介":"果味甜美的 GSM 混釀餐酒",
        "參考價格":429,
        "產區":"Languedoc-Roussillon",
        "國家":"法國",
        "酒莊(廠)":"Valatiere",
        "葡萄品種":"Grenache(33%) ,Syrah (33%) ,Mourvedre (34%)",
        "購買通路":"大潤發",
        "年份":"2022年",
        "酒精濃度":0.135,
        "甜度":1,
        "酸度":4,
        "飽滿度":5,
        "適合搭配食物":"牛排",
        "品酒筆記":"來自於南法 Languedoc-Roussillon 的地區餐酒，以Grenache、Syrah and Mourvedre 調配而成，又稱Ｇ.S.M，是南法地區很常見的調配方式。\n\n帶有甜美的草莓、糖漬水果與甜菸草香氣，口感柔順，還帶有淡淡的木質調性，單寧柔軟，談不上複雜度，就是之前去南法時，日常喝到的餐酒，搭配牛排或是燉肉都可以。3.5顆星的日常餐酒。",
        "URL":"https:\/\/littlewine.com.tw\/wine\/Detail.aspx?title=%e6%9e%9c%e5%91%b3%e7%94%9c%e7%be%8e%e7%9a%84+GSM+%e6%b7%b7%e9%87%80%e9%a4%90%e9%85%92&Wine=%e6%b3%95%e5%9c%8b%e5%8d%97%e6%b3%95%e7%a9%86%e9%9b%b7%e8%92%82GSM%e6%b7%b7%e9%87%80%e7%b4%85%e9%85%92"
    },
    {
        "酒名":"Chateau d'Aiguilhe",
        "簡介":"口感高雅的的波爾多Cotes de Castillon 產區紅酒",
        "參考價格":719,
        "產區":"Cotes de Castillon",
        "國家":"法國",
        "酒莊(廠)":"Chateau d'Aiguilhe",
        "葡萄品種":"Merlot(90%) ,Cabernet Franc (10%)",
        "購買通路":"好市多",
        "年份":"2020年",
        "酒精濃度":0.145,
        "甜度":1,
        "酸度":4,
        "飽滿度":5,
        "適合搭配食物":"羊排,牛排",
        "品酒筆記":"來自於波爾多右岸的名門酒莊 Chateau d'Aiguilhe，這一瓶產區來自於Cotes de Castillon 產區，以90% Merlot 10% Cabernet Franc 混合而成。\n\n整瓶酒的質感無論是酒標或是封籤都很有貴族的風範。\n\n酒色暗紅邊緣帶紫充滿活力，濃郁的黑莓與細緻不搶戲的木桶調性，單寧中上，一開始會覺得比較澀口，但不至於刮舌，整體給人一種優雅高貴的感覺，建議建議醒酒1小時以上，或是過幾年再喝。價錢十分優惠，是款值得入手，在酒櫃保存2-3年的酒款。4顆星推薦。",
        "URL":"https:\/\/littlewine.com.tw\/wine\/Detail.aspx?title=%e5%8f%a3%e6%84%9f%e9%ab%98%e9%9b%85%e7%9a%84%e7%9a%84%e6%b3%a2%e7%88%be%e5%a4%9aCotes+de+Castillon+%e7%94%a2%e5%8d%80%e7%b4%85%e9%85%92&Wine=Chateau+d%27Aiguilhe"
    },
    {
        "酒名":"Motif Cabernet Sauvignon red hills",
        "簡介":"甜美柔滑的美國酒",
        "參考價格":299,
        "產區":"Red hills lake county AVA",
        "國家":"美國",
        "酒莊(廠)":"Motif",
        "葡萄品種":"Cabernet Sauvignon(100%)",
        "購買通路":"好市多",
        "年份":"2022年",
        "酒精濃度":0.145,
        "甜度":1,
        "酸度":4,
        "飽滿度":5,
        "適合搭配食物":"牛排",
        "品酒筆記":"來自於美國 Red hills lake county AVA 產區的卡本內蘇維翁，帶有甜美的黑李子蜜餞風味，口感柔滑，單寧柔順，談不上什麼複雜度，就是款開瓶就好喝，又不會過於甜膩的日常餐酒，適合搭配牛排也很適合新手的入門酒款。4顆星。",
        "URL":"https:\/\/littlewine.com.tw\/wine\/Detail.aspx?title=%e7%94%9c%e7%be%8e%e6%9f%94%e6%bb%91%e7%9a%84%e7%be%8e%e5%9c%8b%e9%85%92&Wine=Motif+Cabernet+Sauvignon+red+hills"
    },
    {
        "酒名":"Combe Rocher Chardonnay",
        "簡介":"跟烤魚下巴超搭的南法 Chardonnay",
        "參考價格":350,
        "產區":"法國 Pay's D'oc",
        "國家":"法國",
        "酒莊(廠)":"Combe Rocher",
        "葡萄品種":"Chardonnay(100%)",
        "購買通路":"大潤發",
        "年份":"2023年",
        "酒精濃度":0.14,
        "甜度":1,
        "酸度":3,
        "飽滿度":5,
        "適合搭配食物":"烤魚下巴",
        "品酒筆記":"這款來自於南法的餐酒等級的Charnanny，帶有熱帶水果香氣以及淡淡的木桶香氣，跟撒上胡椒鹽的魚下巴超級搭配。",
        "URL":"https:\/\/littlewine.com.tw\/wine\/Detail.aspx?title=%e8%b7%9f%e7%83%a4%e9%ad%9a%e4%b8%8b%e5%b7%b4%e8%b6%85%e6%90%ad%e7%9a%84%e5%8d%97%e6%b3%95+Chardonnay&Wine=Combe+Rocher+Chardonnay"
    },
    {
        "酒名":"Ségla 二軍紅酒",
        "簡介":"細緻優雅的波爾多二軍紅酒",
        "參考價格":2000,
        "產區":"Margaux",
        "國家":"法國",
        "酒莊(廠)":"Chateau Rauzan-Ségla",
        "葡萄品種":"波爾多混釀(100%)",
        "購買通路":"法蘭絲",
        "年份":"2017年",
        "酒精濃度":0.135,
        "甜度":1,
        "酸度":4,
        "飽滿度":5,
        "適合搭配食物":"牛排",
        "品酒筆記":"波爾多二級酒莊 Segla 二軍紅酒，帶有明顯的木桶香氣混合黑色水果香氣，口感優雅，單寧適中搭配肋眼、紐約客牛排相當不錯。",
        "URL":"https:\/\/littlewine.com.tw\/wine\/Detail.aspx?title=%e7%b4%b0%e7%b7%bb%e5%84%aa%e9%9b%85%e7%9a%84%e6%b3%a2%e7%88%be%e5%a4%9a%e4%ba%8c%e8%bb%8d%e7%b4%85%e9%85%92&Wine=S%c3%a9gla+%e4%ba%8c%e8%bb%8d%e7%b4%85%e9%85%92"
    },
    {
        "酒名":"Champagne Cheurlin Noellat Carte d’Or Brut NV",
        "簡介":"Champagne Cheurlin Noellat Carte d’Or Brut NV",
        "參考價格":2100,
        "產區":"Champagne",
        "國家":"法國",
        "酒莊(廠)":"Champagne Cheurlin Noellat",
        "葡萄品種":"Pinot Noir(100%)",
        "購買通路":"綠手說",
        "年份":"無年",
        "酒精濃度":0.12,
        "甜度":1,
        "酸度":4,
        "飽滿度":5,
        "適合搭配食物":"干貝",
        "品酒筆記":"帶有爆滿複雜的果味，青蘋果、柑橘、葡萄柚以及百香果，氣泡細緻，酸度適中，跟干貝、鮭魚都超搭。",
        "URL":"https:\/\/littlewine.com.tw\/wine\/Detail.aspx?title=Champagne+Cheurlin+Noellat+Carte+d%e2%80%99Or+Brut+NV&Wine=Champagne+Cheurlin+Noellat+Carte+d%e2%80%99Or+Brut+NV"
    },
    {
        "酒名":"Wynns Black Label Shiraz\n",
        "簡介":"口感絲滑飽滿的澳洲老藤 Shiraz",
        "參考價格":1650,
        "產區":"Coonawarra",
        "國家":"澳洲",
        "酒莊(廠)":"Wynns",
        "葡萄品種":"Shiraz(100%)",
        "購買通路":"Wine O'Clock,LOCA Co",
        "年份":"2018年",
        "酒精濃度":0.138,
        "甜度":1,
        "酸度":4,
        "飽滿度":5,
        "適合搭配食物":"燒烤牛",
        "品酒筆記":"老藤 Shiraz，在法國全新及舊(30%新)橡木桶中陳放14個月，帶有黑色水果與適度的辛香料，口感飽滿絲滑，單寧如天鵝絨般柔順。",
        "URL":"https:\/\/littlewine.com.tw\/wine\/Detail.aspx?title=%e5%8f%a3%e6%84%9f%e7%b5%b2%e6%bb%91%e9%a3%bd%e6%bb%bf%e7%9a%84%e6%be%b3%e6%b4%b2%e8%80%81%e8%97%a4+Shiraz&Wine=Wynns+Black+Label+Shiraz"
    },
    {
        "酒名":"Wynns Coonawarra Estate Cabernet Shiraz Merlot Malbec",
        "簡介":"香氣複雜平易近人的澳洲混釀",
        "參考價格":1050,
        "產區":"Coonawarra",
        "國家":"澳洲",
        "酒莊(廠)":"Wynns Coonawarra Estate",
        "葡萄品種":"Cabernet Shiraz Merlot and Malbec(100%)",
        "購買通路":"\nWine O'Clock,LOCA Co",
        "年份":"2022年",
        "酒精濃度":0.136,
        "甜度":1,
        "酸度":4,
        "飽滿度":5,
        "適合搭配食物":"牛排",
        "品酒筆記":"澳洲 Coonawarra 產區中，WYNNS 酒莊就是這產區內最知名的先驅酒莊之一，連世界葡萄酒地圖一書中也特別標示這個酒莊。\n\n這款也是他們家第一款混釀酒款，以四種葡萄混合而成，帶有複雜的果香，包含黑色水果、黑李、黑醋栗以、紫羅蘭及些微的辛香料。\n\n雖然有於法國橡木桶與豬頭桶熟陳18個月，但是桶味控制的很好，沒有太明顯的木桶痕跡，酒體中上，單寧有存在感，但不會覺得過於澀口，算一款頗為細緻輕鬆易喝的澳洲酒款。4顆星。",
        "URL":"https:\/\/littlewine.com.tw\/wine\/Detail.aspx?title=%e9%a6%99%e6%b0%a3%e8%a4%87%e9%9b%9c%e5%b9%b3%e6%98%93%e8%bf%91%e4%ba%ba%e7%9a%84%e6%be%b3%e6%b4%b2%e6%b7%b7%e9%87%80&Wine=Wynns+Coonawarra+Estate+Cabernet+Shiraz+Merlot+Malbec"
    },
    {
        "酒名":"Albert Bichot Gevrey-Chambertin Reserve de l' Orangerie",
        "簡介":"香氣撲鼻的 Gevrey-Chambertin",
        "參考價格":2099,
        "產區":"Gevrey-Chambertin",
        "國家":"法國",
        "酒莊(廠)":"Albert Bichot",
        "葡萄品種":"Pinot Noir(100%)",
        "購買通路":"好市多",
        "年份":"2018年",
        "酒精濃度":0.135,
        "甜度":1,
        "酸度":5,
        "飽滿度":5,
        "適合搭配食物":"\n牛排",
        "品酒筆記":"非常香！！！ 把酒倒出酒杯就聞到香氣了！\n\n迷人優雅的花香、夾帶些許辛香料，口感渾厚中帶些優雅，單寧收斂感明顯但不咬口；開瓶1小時後，開始多出一些梅子乾與洛神花香味；留了半瓶放到隔天，口感依舊飽滿，尾韻綿長。4顆星\n\n本來以為這個可能要醒更久或是要多放幾年才可以喝，但是現在開瓶大約醒個2小時香氣跟單寧的平衡感就很不錯，是款可以繼續陳放，現在喝也不會太可惜的 Gevrey-Chambertin。",
        "URL":"https:\/\/littlewine.com.tw\/wine\/Detail.aspx?title=%e9%a6%99%e6%b0%a3%e6%92%b2%e9%bc%bb%e7%9a%84+Gevrey-Chambertin+&Wine=Albert+Bichot+Gevrey-Chambertin+Reserve+de+l%27+Orangerie"
    },
    {
        "酒名":"Pyamid Scheme Cabernet Sauvignon",
        "簡介":"甜美不膩的美國卡本內",
        "參考價格":599,
        "產區":"California",
        "國家":"美國",
        "酒莊(廠)":"Pyamid Scheme",
        "葡萄品種":"Cabernet Sauvignon(100%)",
        "購買通路":"全聯",
        "年份":"2021年",
        "酒精濃度":0.138,
        "甜度":1,
        "酸度":3,
        "飽滿度":5,
        "適合搭配食物":"牛排",
        "品酒筆記":"美國知名大廠 Precision 旗下的酒款。紅黑色水果香氣、香料味明顯，口感飽滿，單寧適中，尾韻甜美中帶些適度的丁香與烘烤桶風味。3.5顆星。\n\n",
        "URL":"https:\/\/littlewine.com.tw\/wine\/Detail.aspx?title=%e7%94%9c%e7%be%8e%e4%b8%8d%e8%86%a9%e7%9a%84%e7%be%8e%e5%9c%8b%e5%8d%a1%e6%9c%ac%e5%85%a7&Wine=Pyamid+Scheme+Cabernet+Sauvignon"
    },
    {
        "酒名":"Pyamid Scheme Pinot Noir",
        "簡介":"甜美不膩的加州黑皮諾",
        "參考價格":599,
        "產區":"California",
        "國家":"美國",
        "酒莊(廠)":"Pyamid Scheme",
        "葡萄品種":"Pinot Noir(100%)",
        "購買通路":"全聯",
        "年份":"2021年",
        "酒精濃度":0.135,
        "甜度":1,
        "酸度":4,
        "飽滿度":5,
        "適合搭配食物":"燒烤",
        "品酒筆記":"口感濃郁柔順，但很難直接聯想是黑皮諾。帶有紅色蜜餞果香，伴隨明顯的丁香，有著不錯的酸度，口感中上，單寧柔順，有著不錯的酸度，喝起來甜美不膩，適合搭配燒烤牛排。",
        "URL":"https:\/\/littlewine.com.tw\/wine\/Detail.aspx?title=%e7%94%9c%e7%be%8e%e4%b8%8d%e8%86%a9%e7%9a%84%e5%8a%a0%e5%b7%9e%e9%bb%91%e7%9a%ae%e8%ab%be&Wine=Pyamid+Scheme+Pinot+Noir"
    },
    {
        "酒名":"Stark conde Stark conde Vineyard selection Cabernet Sauvignon",
        "簡介":"飽滿好喝的南非Cabernet Sauvignon",
        "參考價格":429,
        "產區":"Coastal",
        "國家":"南非",
        "酒莊(廠)":"Stark conde",
        "葡萄品種":"Cabernet Sauvignon,petit verdot, malbec, petite sirah cnd cab franc(100%)",
        "購買通路":"好市多",
        "年份":"2022年",
        "酒精濃度":0.14,
        "甜度":1,
        "酸度":4,
        "飽滿度":5,
        "適合搭配食物":"牛排",
        "品酒筆記":"來自於南非知名的酒莊 Stark conde，網路上找不到這款資訊，不確定是不是改酒標，但是跟之前好市多同酒廠的品種組合跟產區都有點不同，所以姑且先列為新品。\n\n帶有黑色水果、黑莓、菸草與大地氣息，迷人的酸度，單寧適切口感優雅，適合搭配牛排。4顆星。",
        "URL":"https:\/\/littlewine.com.tw\/wine\/Detail.aspx?title=%e9%a3%bd%e6%bb%bf%e5%a5%bd%e5%96%9d%e7%9a%84%e5%8d%97%e9%9d%9eCabernet+Sauvignon&Wine=Stark+conde+Stark+conde+Vineyard+selection+Cabernet+Sauvignon"
    },
    {
        "酒名":"1895 Rosso",
        "簡介":"4.5 顆星推薦的義大利 Toscana 紅酒",
        "參考價格":459,
        "產區":"Toscana",
        "國家":"義大利",
        "酒莊(廠)":"Verga La Storia",
        "葡萄品種":"Sangiovese 混合Cabernet and Merlot(100%)",
        "購買通路":"大潤發",
        "年份":"2022年",
        "酒精濃度":0.14,
        "甜度":1,
        "酸度":4,
        "飽滿度":4,
        "適合搭配食物":"紅醬義大利麵,辛香料的食物",
        "品酒筆記":"來自於Toscana 產區，以Sangiovese 為主，混合Cabernet and Merlot品種。\n\n帶有迷人的黑莓、可可與辛香料的香氣，酒體中等，單寧細緻，口感非常均衡，而且開瓶就好喝，完全不需要醒。\n\n而且瓶身厚重，看起來高大上，帶去朋友聚會絕對不會丟臉，重點是價錢非常優惠，4.5顆星推薦，必買！！！",
        "URL":"https:\/\/littlewine.com.tw\/wine\/Detail.aspx?title=4.5+%e9%a1%86%e6%98%9f%e6%8e%a8%e8%96%a6%e7%9a%84%e7%be%a9%e5%a4%a7%e5%88%a9+Toscana+%e7%b4%85%e9%85%92&Wine=1895+Rosso"
    },
    {
        "酒名":"Hans Greyl New Zealand Marlborough Sauvignon Blanc",
        "簡介":"跟生魚片、辣炒年糕都能搭配的紐西蘭白蘇維翁",
        "參考價格":369,
        "產區":"Marlborough",
        "國家":"紐西蘭",
        "酒莊(廠)":"Hans Greyl",
        "葡萄品種":"Sauvignon Blanc(100%)",
        "購買通路":"大潤發",
        "年份":"2022年",
        "酒精濃度":0.12,
        "甜度":1,
        "酸度":4,
        "飽滿度":4,
        "適合搭配食物":"生魚片",
        "品酒筆記":"有明顯百香果香氣、酸度舒適，搭配透抽生魚片，果味爆棚鮮度加倍，另外也嘗試搭配韓式辣炒年糕，能解膩緩和辣味。4顆星",
        "URL":"https:\/\/littlewine.com.tw\/wine\/Detail.aspx?title=%e8%b7%9f%e7%94%9f%e9%ad%9a%e7%89%87%e3%80%81%e8%be%a3%e7%82%92%e5%b9%b4%e7%b3%95%e9%83%bd%e8%83%bd%e6%90%ad%e9%85%8d%e7%9a%84%e7%b4%90%e8%a5%bf%e8%98%ad%e7%99%bd%e8%98%87%e7%b6%ad%e7%bf%81&Wine=Hans+Greyl+New+Zealand+Marlborough+Sauvignon+Blanc"
    },
    {
        "酒名":"Kid D'Arsac 法國波爾多亞薩克堡之子二軍紅酒",
        "簡介":"口感優雅的Margaux產區紅酒",
        "參考價格":759,
        "產區":"Margaux",
        "國家":"法國",
        "酒莊(廠)":"Kid D'Arsac",
        "葡萄品種":"波爾多混釀(100%)",
        "購買通路":"大潤發",
        "年份":"2019年",
        "酒精濃度":0.14,
        "甜度":1,
        "酸度":4,
        "飽滿度":5,
        "適合搭配食物":"羊排",
        "品酒筆記":"來自於法國波爾多左岸Margaux產區，帶有迷人的黑醋栗以及木桶香氣，口感優雅，單寧如天鵝絨般柔順，建議醒酒1小時以上，大賣場的這價位，很值！！4顆星。",
        "URL":"https:\/\/littlewine.com.tw\/wine\/Detail.aspx?title=%e5%8f%a3%e6%84%9f%e5%84%aa%e9%9b%85%e7%9a%84Margaux%e7%94%a2%e5%8d%80%e7%b4%85%e9%85%92&Wine=Kid+D%27Arsac+%e6%b3%95%e5%9c%8b%e6%b3%a2%e7%88%be%e5%a4%9a%e4%ba%9e%e8%96%a9%e5%85%8b%e5%a0%a1%e4%b9%8b%e5%ad%90%e4%ba%8c%e8%bb%8d%e7%b4%85%e9%85%92"
    },
    {
        "酒名":"Metz Road Riverview Vineyard Pinot Noir",
        "簡介":"細緻的美國黑皮諾",
        "參考價格":799,
        "產區":"MONTEREY",
        "國家":"美國",
        "酒莊(廠)":"Metz Road",
        "葡萄品種":"Pinot Noir(100%)",
        "購買通路":"大潤發",
        "年份":"2020年",
        "酒精濃度":0.145,
        "甜度":1,
        "酸度":4,
        "飽滿度":5,
        "適合搭配食物":"牛排",
        "品酒筆記":"來自於美國較為冷涼的MONTEREY產區，以100%法國橡木桶陳放13個月，帶有草莓、乾燥玫瑰以及些許洛神花香氣，酸度迷人，單寧細緻。雖然是美國的 Pinot Noir，但是喝起來比預期的輕柔，比紐西蘭的更濃郁，喝起來也勝過一些勃根地大區的酒款，相當不錯。4顆星推薦。",
        "URL":"https:\/\/littlewine.com.tw\/wine\/Detail.aspx?title=%e7%b4%b0%e7%b7%bb%e7%9a%84%e7%be%8e%e5%9c%8b%e9%bb%91%e7%9a%ae%e8%ab%be&Wine=Metz+Road+Riverview+Vineyard+Pinot+Noir"
    },
    {
        "酒名":"Aristotle Petite Sirah",
        "簡介":"果味濃郁單寧優雅的 Petite Sirah",
        "參考價格":469,
        "產區":"Monterey County",
        "國家":"美國",
        "酒莊(廠)":"Aristotle",
        "葡萄品種":"Petite Sirah(100%)",
        "購買通路":"大潤發",
        "年份":"2021年",
        "酒精濃度":0.135,
        "甜度":1,
        "酸度":4,
        "飽滿度":5,
        "適合搭配食物":"牛排",
        "品酒筆記":"來自美國加州較為冷涼的 Monterey 產區，以有機葡萄釀造，在全新法國橡木桶熟成10個月，果香濃郁突出，單寧優雅，細緻的辛香料交織出果味甜美口感細柔的 Petite Sirah。4顆星。",
        "URL":"https:\/\/littlewine.com.tw\/wine\/Detail.aspx?title=%e6%9e%9c%e5%91%b3%e6%bf%83%e9%83%81%e5%96%ae%e5%af%a7%e5%84%aa%e9%9b%85%e7%9a%84+Petite+Sirah&Wine=Aristotle+Petite+Sirah"
    },
    {
        "酒名":"Paso Point Syrah Lot 9",
        "簡介":"煙燻明顯的美國 Syrah",
        "參考價格":449,
        "產區":"California",
        "國家":"美國",
        "酒莊(廠)":"Paso Point",
        "葡萄品種":"Syrah(100%)",
        "購買通路":"大潤發",
        "年份":"2020年",
        "酒精濃度":0.145,
        "甜度":1,
        "酸度":4,
        "飽滿度":5,
        "適合搭配食物":"\n煙燻牛小排",
        "品酒筆記":"Paso Point Syrah Lot 9。明顯的煙燻肉乾以及烘烤桶味道，同時伴隨些許辛香料，口感飽滿甜美，單寧有存在感，適合搭配煙燻牛小排的肉類。3.5顆星",
        "URL":"https:\/\/littlewine.com.tw\/wine\/Detail.aspx?title=%e7%85%99%e7%87%bb%e6%98%8e%e9%a1%af%e7%9a%84%e7%be%8e%e5%9c%8b+Syrah&Wine=Paso+Point+Syrah+Lot+9"
    },
    {
        "酒名":"Monasterio De Las Vinas Gran Reserva 2017",
        "簡介":"香氣與口感複雜度都很不錯的西班牙混釀",
        "參考價格":529,
        "產區":"Cariñena",
        "國家":"西班牙",
        "酒莊(廠)":"Grandes Vinos",
        "葡萄品種":"Garnacha, Cariñena and Tempranillo 混釀(100%)",
        "購買通路":"大潤發",
        "年份":"2017年",
        "酒精濃度":0.14,
        "甜度":1,
        "酸度":4,
        "飽滿度":4,
        "適合搭配食物":"燒烤類食物",
        "品酒筆記":"24 個月橡木桶熟成，50%法國桶、50%美國桶。帶有些許皮革與香料風味，酒體中偏淡，單寧適中，口感雖然不是非常強壯飽滿，但是香氣與口感的複雜度佳，建議醒酒1小時左右。\n這款大潤發之前就推出過，是一款很穩定的酒款，這次再回來，價錢雖然稍微貴了約100元，但是還算是可以接受。",
        "URL":"https:\/\/littlewine.com.tw\/wine\/Detail.aspx?title=%e9%a6%99%e6%b0%a3%e8%88%87%e5%8f%a3%e6%84%9f%e8%a4%87%e9%9b%9c%e5%ba%a6%e9%83%bd%e5%be%88%e4%b8%8d%e9%8c%af%e7%9a%84%e8%a5%bf%e7%8f%ad%e7%89%99%e6%b7%b7%e9%87%80&Wine=Monasterio+De+Las+Vinas+Gran+Reserva+2017"
    },
    {
        "酒名":"Bêê Bêê Pinot noir 隆格多克咩咩羊黑皮諾紅酒",
        "簡介":"輕鬆搭餐的南法黑皮諾",
        "參考價格":389,
        "產區":"Languedoc Pays d'oc",
        "國家":"法國",
        "酒莊(廠)":"Bêê Bêê",
        "葡萄品種":"Pinot noir(100%)",
        "購買通路":"大潤發",
        "年份":"2023年",
        "酒精濃度":0.13,
        "甜度":1,
        "酸度":3,
        "飽滿度":3,
        "適合搭配食物":"清淡中式台菜",
        "品酒筆記":"草莓、花香以及淡淡木桶香氣，口感輕柔，酸度高，是款輕鬆的搭餐酒。",
        "URL":"https:\/\/littlewine.com.tw\/wine\/Detail.aspx?title=%e8%bc%95%e9%ac%86%e6%90%ad%e9%a4%90%e7%9a%84%e5%8d%97%e6%b3%95%e9%bb%91%e7%9a%ae%e8%ab%be&Wine=B%c3%aa%c3%aa+B%c3%aa%c3%aa+Pinot+noir+%e9%9a%86%e6%a0%bc%e5%a4%9a%e5%85%8b%e5%92%a9%e5%92%a9%e7%be%8a%e9%bb%91%e7%9a%ae%e8%ab%be%e7%b4%85%e9%85%92"
    },
    {
        "酒名":"Domaine Olivier Clos Faguesche",
        "簡介":"多汁可口的Cabernet Franc",
        "參考價格":499,
        "產區":"Bourgueil, Touraine, Loire,",
        "國家":"法國",
        "酒莊(廠)":"Domaine Olivier",
        "葡萄品種":"Cabernet Franc(100%)",
        "購買通路":"大潤發",
        "年份":"2020年",
        "酒精濃度":0.125,
        "甜度":1,
        "酸度":4,
        "飽滿度":4,
        "適合搭配食物":"燒烤",
        "品酒筆記":"100% Cabernet Franc釀造，黑色水果混合青草香氣，口感輕柔，酸度宜人，非常多汁可口。4顆星推薦",
        "URL":"https:\/\/littlewine.com.tw\/wine\/Detail.aspx?title=%e5%a4%9a%e6%b1%81%e5%8f%af%e5%8f%a3%e7%9a%84Cabernet+Franc&Wine=Domaine+Olivier+Clos+Faguesche"
    },
    {
        "酒名":"Chateau De Pennautier Terroir D'Altitude",
        "簡介":"法國隆格多克彭娜蒂莊園紅酒",
        "參考價格":499,
        "產區":"Cabardes",
        "國家":"法國",
        "酒莊(廠)":"Chateau De Pennautier",
        "葡萄品種":"Grenache(30%) ,Syrah (25%) ,Malbec (15%) ,Cinsault (10%) ,Cabernet\/ and Merlot (15%)",
        "購買通路":"大潤發",
        "年份":"2018年",
        "酒精濃度":0.145,
        "甜度":1,
        "酸度":4,
        "飽滿度":5,
        "適合搭配食物":"牛排",
        "品酒筆記":"法國隆格多克產區的紅酒，這款橡木桶陳釀12個月，帶有仙草乾茶、黑色水果、輕微煙燻與香草氣息，口感飽滿，單寧明顯，建議醒酒1小時。",
        "URL":"https:\/\/littlewine.com.tw\/wine\/Detail.aspx?title=%e6%b3%95%e5%9c%8b%e9%9a%86%e6%a0%bc%e5%a4%9a%e5%85%8b%e5%bd%ad%e5%a8%9c%e8%92%82%e8%8e%8a%e5%9c%92%e7%b4%85%e9%85%92&Wine=Chateau+De+Pennautier+Terroir+D%27Altitude"
    }
]